.gitignore
CMakeLists.txt
LICENSE
README.md
pyproject.toml
setup.py
_skbuild/linux-x86_64-3.9/cmake-install/.gitignore
_skbuild/linux-x86_64-3.9/cmake-install/CMakeLists.txt
_skbuild/linux-x86_64-3.9/cmake-install/README.md
_skbuild/linux-x86_64-3.9/cmake-install/nanobbox_ext.cpython-39-x86_64-linux-gnu.so
_skbuild/linux-x86_64-3.9/cmake-install/pyproject.toml
_skbuild/linux-x86_64-3.9/cmake-install/setup.py
_skbuild/linux-x86_64-3.9/cmake-install/benchmark/benchmark.py
_skbuild/linux-x86_64-3.9/cmake-install/src/nanobbox_ext.cpp
_skbuild/linux-x86_64-3.9/cmake-install/src/nanobbox/__init__.py
_skbuild/linux-x86_64-3.9/cmake-install/src/nanobbox/nanobbox_ext.cpython-39-x86_64-linux-gnu.so
_skbuild/linux-x86_64-3.9/cmake-install/src/nanobbox/setup.py
_skbuild/linux-x86_64-3.9/cmake-install/src/nanobbox/src/nanobbox/__init__.py
benchmark/benchmark.py
src/nanobbox_ext.cpp
src/nanobbox/__init__.py
src/nanobbox.egg-info/PKG-INFO
src/nanobbox.egg-info/SOURCES.txt
src/nanobbox.egg-info/dependency_links.txt
src/nanobbox.egg-info/top_level.txt