Metadata-Version: 2.1
Name: nanobbox
Version: 0.4.0
Summary: A bbox project that compiles bindings using nanobind and scikit-build
Home-page: https://github.com/neka-nat/nanobbox
Author: neka-nat
Author-email: nekanat.stock@gmail.com
License: MIT
Platform: UNKNOWN
Requires-Python: >=3.8
License-File: LICENSE
